multisat/__init__.py
multisat/converter.py
multisat/harmonizer.py
multisat/resampler.py
multisat/utils.py
multisat-1.0.1.dist-info/licenses/LICENSE
multisat-1.0.1.dist-info/METADATA
multisat-1.0.1.dist-info/WHEEL
multisat-1.0.1.dist-info/top_level.txt
multisat-1.0.1.dist-info/RECORD
