Metadata-Version: 2.4
Name: multisat
Version: 1.0.1
Summary: A Python library to convert, resample, and harmonize satellite imagery across different sources.
Home-page: https://github.com/yourusername/multisat
Author: Sujal Bandodkar
Author-email: sujalbandodkar05@gmail.com
Classifier: Development Status :: 4 - Beta
Classifier: Intended Audience :: Science/Research
Classifier: Topic :: Scientific/Engineering :: GIS
Classifier: License :: OSI Approved :: MIT License
Classifier: Programming Language :: Python :: 3
Classifier: Operating System :: OS Independent
Requires-Python: >=3.7
License-File: LICENSE
Requires-Dist: rasterio>=1.3.0
Requires-Dist: numpy>=1.20
Requires-Dist: gdal>=3.7.0
Requires-Dist: scikit-image>=0.19
Requires-Dist: matplotlib>=3.3
Dynamic: author
Dynamic: author-email
Dynamic: classifier
Dynamic: description
Dynamic: description-content-type
Dynamic: home-page
Dynamic: license-file
Dynamic: requires-dist
Dynamic: requires-python
Dynamic: summary
